asp_clean/__init__.py
asp_clean/compose.py
asp_clean/load.py
asp_clean/parse.py
asp_clean/report.py
asp_clean-0.1.1.dist-info/WHEEL
asp_clean-0.1.1.dist-info/METADATA
asp_clean-0.1.1.dist-info/RECORD
