Metadata-Version: 2.1
Name: asp-clean
Version: 0.1.1
Summary: 
Author: YewtsingMu
Author-email: mooyewtsing@gmail.com
Requires-Python: >=3.6.9,<4.0.0
Classifier: Programming Language :: Python :: 3
Classifier: Programming Language :: Python :: 3.7
Classifier: Programming Language :: Python :: 3.8
Requires-Dist: openpyxl (>=3.0.5,<4.0.0)
Requires-Dist: requests (>=2.24.0,<3.0.0)
Requires-Dist: toolz (>=0.10.0,<0.11.0)
